post_archiver_improved/__init__.py
post_archiver_improved/api.py
post_archiver_improved/cli.py
post_archiver_improved/comment_processor.py
post_archiver_improved/config.py
post_archiver_improved/constants.py
post_archiver_improved/exceptions.py
post_archiver_improved/extractors.py
post_archiver_improved/logging_config.py
post_archiver_improved/models.py
post_archiver_improved/output.py
post_archiver_improved/py.typed
post_archiver_improved/scraper.py
post_archiver_improved/utils.py
post_archiver_improved-0.3.0.dist-info/licenses/LICENSE
post_archiver_improved-0.3.0.dist-info/METADATA
post_archiver_improved-0.3.0.dist-info/WHEEL
post_archiver_improved-0.3.0.dist-info/entry_points.txt
post_archiver_improved-0.3.0.dist-info/top_level.txt
post_archiver_improved-0.3.0.dist-info/RECORD
